Workbook

Sheet Inicio
B2: GERENCIADOR DE IMPOSTO DE RENDA
B5: Painel financeiro para organização, conferência e estimativa fiscal
B8: 📊 DASHBOARD Visão executiva e indicadores | D8: ＋ LANÇAMENTOS Cadastre e revise movimentações
B13: ⚙ TABELAS DE APOIO Categorias e parâmetros | D13: ✓ FLUXO RECOMENDADO 1. Lance dados 2. Revise categorias 3. Consulte o dashboard
B27: Projeto demonstrativo de Excel aplicado à organização financeira.

Sheet Tabelas_Apoio
A1: TABELAS DE APOIO
A2: Parâmetros utilizados pelas validações e pelo cálculo automático.
A4: Categoria | B4: Tipo | C4: Base Mínima | D4: Base Máxima | E4: Alíquota | F4: Parcela a Deduzir
A5: Rendimento de Trabalho Assalariado | B5: Tributável | C5: 0 | D5: 27110.4 | E5: 0 | F5: 0
A6: Aposentadorias e Pensões | B6: Tributável | C6: 27110.41 | D6: 33919.8 | E6: 0.075 | F6: 2033.28
A7: Aluguéis Recebidos | B7: Tributável | C7: 33919.81 | D7: 45012.6 | E7: 0.15 | F7: 4577.27
A8: Rendimentos de Poupança / LCI / LCA | B8: Isento | C8: 45012.61 | D8: 55976.16 | E8: 0.225 | F8: 7953.21
A9: Dividendos e Lucros | B9: Isento | C9: 55976.17 | D9: 9999999 | E9: 0.275 | F9: 10752.02
A10: Instrução / Educação | B10: Dedução
A11: Despesas Médicas e Odontológicas | B11: Dedução
A12: Previdência Privada (PGBL) | B12: Dedução
A13: Pensão Alimentícia Judicial | B13: Dedução

Sheet Lancamentos
A1: LANÇAMENTOS FINANCEIROS
A2: Cadastre rendimentos e despesas. Use a lista de categorias para manter os dados padronizados.
A3: Dica: mantenha descrição, data e documento da fonte preenchidos para facilitar conferência e auditoria.
A4: Data | B4: Descrição | C4: Categoria | D4: Valor (R$) | E4: CNPJ/CPF Fonte
A5: 46027 | B5: Salário Mensal | C5: Rendimento de Trabalho Assalariado | D5: 6500 | E5: 12.345.678/0001-99
A6: 46032 | B6: Mensalidade Faculdade | C6: Instrução / Educação | D6: 450 | E6: 98.765.432/0001-10
A7: 46037 | B7: Consulta Odontológica | C7: Despesas Médicas e Odontológicas | D7: 350 | E7: 111.222.333-44
A8: 46042 | B8: Distribuição de Lucros | C8: Dividendos e Lucros | D8: 1200 | E8: 12.345.678/0001-99

Sheet Dashboard
B2: DASHBOARD FISCAL
B4: Visão executiva dos lançamentos e da estimativa automática do imposto.
B6: ⌂ INÍCIO | C6: ＋ LANÇAMENTOS | D6: ⚙ TABELAS | H6: Ano de análise | I6: 2026
B8: RENDIMENTOS TRIBUTÁVEIS | E8: RENDIMENTOS ISENTOS | H8: DEDUÇÕES PERMITIDAS
B9: =SUMIFS(Lancamentos!$D:$D,Lancamentos!$C:$C,"Rendimento de Trabalho Assalariado",Lancamentos!$A:$A,">="&DATE($I$6,1,1),Lancamentos!$A:$A,"<"&DATE($I$6+1,1,1))+SUMIFS(Lancamentos!$D:$D,Lancamentos!$C:$C,"Aposentadorias e Pensões",Lancamentos!$A:$A,">="&DATE($I$6,1,1),Lancamentos!$A:$A,"<"&DATE($I$6+1,1,1))+SUMIFS(Lancamentos!$D:$D,Lancamentos!$C:$C,"Aluguéis Recebidos",Lancamentos!$A:$A,">="&DATE($I$6,1,1),Lancamentos!$A:$A,"<"&DATE($I$6+1,1,1)) -> 6500 | E9: =SUMIFS(Lancamentos!$D:$D,Lancamentos!$C:$C,"Rendimentos de Poupança / LCI / LCA",Lancamentos!$A:$A,">="&DATE($I$6,1,1),Lancamentos!$A:$A,"<"&DATE($I$6+1,1,1))+SUMIFS(Lancamentos!$D:$D,Lancamentos!$C:$C,"Dividendos e Lucros",Lancamentos!$A:$A,">="&DATE($I$6,1,1),Lancamentos!$A:$A,"<"&DATE($I$6+1,1,1)) -> 1200 | H9: =SUMIFS(Lancamentos!$D:$D,Lancamentos!$C:$C,"Instrução / Educação",Lancamentos!$A:$A,">="&DATE($I$6,1,1),Lancamentos!$A:$A,"<"&DATE($I$6+1,1,1))+SUMIFS(Lancamentos!$D:$D,Lancamentos!$C:$C,"Despesas Médicas e Odontológicas",Lancamentos!$A:$A,">="&DATE($I$6,1,1),Lancamentos!$A:$A,"<"&DATE($I$6+1,1,1))+SUMIFS(Lancamentos!$D:$D,Lancamentos!$C:$C,"Previdência Privada (PGBL)",Lancamentos!$A:$A,">="&DATE($I$6,1,1),Lancamentos!$A:$A,"<"&DATE($I$6+1,1,1))+SUMIFS(Lancamentos!$D:$D,Lancamentos!$C:$C,"Pensão Alimentícia Judicial",Lancamentos!$A:$A,">="&DATE($I$6,1,1),Lancamentos!$A:$A,"<"&DATE($I$6+1,1,1)) -> 800
B13: BASE DE CÁLCULO | E13: ALÍQUOTA EFETIVA | H13: IMPOSTO ESTIMADO
B14: =MAX(0,B9-H9) -> 5700 | E14: =IFERROR(VLOOKUP(B14,Tabelas_Apoio!$C$5:$F$9,3,TRUE),0) -> 0 | H14: =MAX(0,B14*E14-IFERROR(VLOOKUP(B14,Tabelas_Apoio!$C$5:$F$9,4,TRUE),0)) -> 0
B18: ANÁLISE AUTOMÁTICA
B19: =IF(H14=0,"✓ Nenhum imposto estimado com os lançamentos atuais.",IF(H14<1000,"● Imposto estimado abaixo de R$ 1.000,00. Revise as deduções e os documentos.","▲ Imposto estimado relevante. Revise a base de cálculo e as deduções.")) -> ✓ Nenhum imposto estimado com os lançamentos atuais.
B22: EVOLUÇÃO MENSAL
B23: Mês | C23: Rendimentos | D23: Deduções | E23: Resultado
B24: Jan | C24: =SUMIFS(Lancamentos!$D:$D,Lancamentos!$A:$A,">="&DATE($I$6,1,1),Lancamentos!$A:$A,"<"&EDATE(DATE($I$6,1,1),1),Lancamentos!$C:$C,"Rendimento de Trabalho Assalariado")+SUMIFS(Lancamentos!$D:$D,Lancamentos!$A:$A,">="&DATE($I$6,1,1),Lancamentos!$A:$A,"<"&EDATE(DATE($I$6,1,1),1),Lancamentos!$C:$C,"Aposentadorias e Pensões")+SUMIFS(Lancamentos!$D:$D,Lancamentos!$A:$A,">="&DATE($I$6,1,1),Lancamentos!$A:$A,"<"&EDATE(DATE($I$6,1,1),1),Lancamentos!$C:$C,"Aluguéis Recebidos") -> 6500 | D24: =SUMIFS(Lancamentos!$D:$D,Lancamentos!$A:$A,">="&DATE($I$6,1,1),Lancamentos!$A:$A,"<"&EDATE(DATE($I$6,1,1),1),Lancamentos!$C:$C,"Instrução / Educação")+SUMIFS(Lancamentos!$D:$D,Lancamentos!$A:$A,">="&DATE($I$6,1,1),Lancamentos!$A:$A,"<"&EDATE(DATE($I$6,1,1),1),Lancamentos!$C:$C,"Despesas Médicas e Odontológicas")+SUMIFS(Lancamentos!$D:$D,Lancamentos!$A:$A,">="&DATE($I$6,1,1),Lancamentos!$A:$A,"<"&EDATE(DATE($I$6,1,1),1),Lancamentos!$C:$C,"Previdência Privada (PGBL)")+SUMIFS(Lancamentos!$D:$D,Lancamentos!$A:$A,">="&DATE($I$6,1,1),Lancamentos!$A:$A,"<"&EDATE(DATE($I$6,1,1),1),Lancamentos!$C:$C,"Pensão Alimentícia Judicial") -> 800 | E24: =C24-D24 -> 5700
B25: Fev | C25: =SUMIFS(Lancamentos!$D:$D,Lancamentos!$A:$A,">="&DATE($I$6,2,1),Lancamentos!$A:$A,"<"&EDATE(DATE($I$6,2,1),1),Lancamentos!$C:$C,"Rendimento de Trabalho Assalariado")+SUMIFS(Lancamentos!$D:$D,Lancamentos!$A:$A,">="&DATE($I$6,2,1),Lancamentos!$A:$A,"<"&EDATE(DATE($I$6,2,1),1),Lancamentos!$C:$C,"Aposentadorias e Pensões")+SUMIFS(Lancamentos!$D:$D,Lancamentos!$A:$A,">="&DATE($I$6,2,1),Lancamentos!$A:$A,"<"&EDATE(DATE($I$6,2,1),1),Lancamentos!$C:$C,"Aluguéis Recebidos") -> 0 | D25: =SUMIFS(Lancamentos!$D:$D,Lancamentos!$A:$A,">="&DATE($I$6,2,1),Lancamentos!$A:$A,"<"&EDATE(DATE($I$6,2,1),1),Lancamentos!$C:$C,"Instrução / Educação")+SUMIFS(Lancamentos!$D:$D,Lancamentos!$A:$A,">="&DATE($I$6,2,1),Lancamentos!$A:$A,"<"&EDATE(DATE($I$6,2,1),1),Lancamentos!$C:$C,"Despesas Médicas e Odontológicas")+SUMIFS(Lancamentos!$D:$D,Lancamentos!$A:$A,">="&DATE($I$6,2,1),Lancamentos!$A:$A,"<"&EDATE(DATE($I$6,2,1),1),Lancamentos!$C:$C,"Previdência Privada (PGBL)")+SUMIFS(Lancamentos!$D:$D,Lancamentos!$A:$A,">="&DATE($I$6,2,1),Lancamentos!$A:$A,"<"&EDATE(DATE($I$6,2,1),1),Lancamentos!$C:$C,"Pensão Alimentícia Judicial") -> 0 | E25: =C25-D25 -> 0
B26: Mar | C26: =SUMIFS(Lancamentos!$D:$D,Lancamentos!$A:$A,">="&DATE($I$6,3,1),Lancamentos!$A:$A,"<"&EDATE(DATE($I$6,3,1),1),Lancamentos!$C:$C,"Rendimento de Trabalho Assalariado")+SUMIFS(Lancamentos!$D:$D,Lancamentos!$A:$A,">="&DATE($I$6,3,1),Lancamentos!$A:$A,"<"&EDATE(DATE($I$6,3,1),1),Lancamentos!$C:$C,"Aposentadorias e Pensões")+SUMIFS(Lancamentos!$D:$D,Lancamentos!$A:$A,">="&DATE($I$6,3,1),Lancamentos!$A:$A,"<"&EDATE(DATE($I$6,3,1),1),Lancamentos!$C:$C,"Aluguéis Recebidos") -> 0 | D26: =SUMIFS(Lancamentos!$D:$D,Lancamentos!$A:$A,">="&DATE($I$6,3,1),Lancamentos!$A:$A,"<"&EDATE(DATE($I$6,3,1),1),Lancamentos!$C:$C,"Instrução / Educação")+SUMIFS(Lancamentos!$D:$D,Lancamentos!$A:$A,">="&DATE($I$6,3,1),Lancamentos!$A:$A,"<"&EDATE(DATE($I$6,3,1),1),Lancamentos!$C:$C,"Despesas Médicas e Odontológicas")+SUMIFS(Lancamentos!$D:$D,Lancamentos!$A:$A,">="&DATE($I$6,3,1),Lancamentos!$A:$A,"<"&EDATE(DATE($I$6,3,1),1),Lancamentos!$C:$C,"Previdência Privada (PGBL)")+SUMIFS(Lancamentos!$D:$D,Lancamentos!$A:$A,">="&DATE($I$6,3,1),Lancamentos!$A:$A,"<"&EDATE(DATE($I$6,3,1),1),Lancamentos!$C:$C,"Pensão Alimentícia Judicial") -> 0 | E26: =C26-D26 -> 0
B27: Abr | C27: =SUMIFS(Lancamentos!$D:$D,Lancamentos!$A:$A,">="&DATE($I$6,4,1),Lancamentos!$A:$A,"<"&EDATE(DATE($I$6,4,1),1),Lancamentos!$C:$C,"Rendimento de Trabalho Assalariado")+SUMIFS(Lancamentos!$D:$D,Lancamentos!$A:$A,">="&DATE($I$6,4,1),Lancamentos!$A:$A,"<"&EDATE(DATE($I$6,4,1),1),Lancamentos!$C:$C,"Aposentadorias e Pensões")+SUMIFS(Lancamentos!$D:$D,Lancamentos!$A:$A,">="&DATE($I$6,4,1),Lancamentos!$A:$A,"<"&EDATE(DATE($I$6,4,1),1),Lancamentos!$C:$C,"Aluguéis Recebidos") -> 0 | D27: =SUMIFS(Lancamentos!$D:$D,Lancamentos!$A:$A,">="&DATE($I$6,4,1),Lancamentos!$A:$A,"<"&EDATE(DATE($I$6,4,1),1),Lancamentos!$C:$C,"Instrução / Educação")+SUMIFS(Lancamentos!$D:$D,Lancamentos!$A:$A,">="&DATE($I$6,4,1),Lancamentos!$A:$A,"<"&EDATE(DATE($I$6,4,1),1),Lancamentos!$C:$C,"Despesas Médicas e Odontológicas")+SUMIFS(Lancamentos!$D:$D,Lancamentos!$A:$A,">="&DATE($I$6,4,1),Lancamentos!$A:$A,"<"&EDATE(DATE($I$6,4,1),1),Lancamentos!$C:$C,"Previdência Privada (PGBL)")+SUMIFS(Lancamentos!$D:$D,Lancamentos!$A:$A,">="&DATE($I$6,4,1),Lancamentos!$A:$A,"<"&EDATE(DATE($I$6,4,1),1),Lancamentos!$C:$C,"Pensão Alimentícia Judicial") -> 0 | E27: =C27-D27 -> 0
B28: Mai | C28: =SUMIFS(Lancamentos!$D:$D,Lancamentos!$A:$A,">="&DATE($I$6,5,1),Lancamentos!$A:$A,"<"&EDATE(DATE($I$6,5,1),1),Lancamentos!$C:$C,"Rendimento de Trabalho Assalariado")+SUMIFS(Lancamentos!$D:$D,Lancamentos!$A:$A,">="&DATE($I$6,5,1),Lancamentos!$A:$A,"<"&EDATE(DATE($I$6,5,1),1),Lancamentos!$C:$C,"Aposentadorias e Pensões")+SUMIFS(Lancamentos!$D:$D,Lancamentos!$A:$A,">="&DATE($I$6,5,1),Lancamentos!$A:$A,"<"&EDATE(DATE($I$6,5,1),1),Lancamentos!$C:$C,"Aluguéis Recebidos") -> 0 | D28: =SUMIFS(Lancamentos!$D:$D,Lancamentos!$A:$A,">="&DATE($I$6,5,1),Lancamentos!$A:$A,"<"&EDATE(DATE($I$6,5,1),1),Lancamentos!$C:$C,"Instrução / Educação")+SUMIFS(Lancamentos!$D:$D,Lancamentos!$A:$A,">="&DATE($I$6,5,1),Lancamentos!$A:$A,"<"&EDATE(DATE($I$6,5,1),1),Lancamentos!$C:$C,"Despesas Médicas e Odontológicas")+SUMIFS(Lancamentos!$D:$D,Lancamentos!$A:$A,">="&DATE($I$6,5,1),Lancamentos!$A:$A,"<"&EDATE(DATE($I$6,5,1),1),Lancamentos!$C:$C,"Previdência Privada (PGBL)")+SUMIFS(Lancamentos!$D:$D,Lancamentos!$A:$A,">="&DATE($I$6,5,1),Lancamentos!$A:$A,"<"&EDATE(DATE($I$6,5,1),1),Lancamentos!$C:$C,"Pensão Alimentícia Judicial") -> 0 | E28: =C28-D28 -> 0
B29: Jun | C29: =SUMIFS(Lancamentos!$D:$D,Lancamentos!$A:$A,">="&DATE($I$6,6,1),Lancamentos!$A:$A,"<"&EDATE(DATE($I$6,6,1),1),Lancamentos!$C:$C,"Rendimento de Trabalho Assalariado")+SUMIFS(Lancamentos!$D:$D,Lancamentos!$A:$A,">="&DATE($I$6,6,1),Lancamentos!$A:$A,"<"&EDATE(DATE($I$6,6,1),1),Lancamentos!$C:$C,"Aposentadorias e Pensões")+SUMIFS(Lancamentos!$D:$D,Lancamentos!$A:$A,">="&DATE($I$6,6,1),Lancamentos!$A:$A,"<"&EDATE(DATE($I$6,6,1),1),Lancamentos!$C:$C,"Aluguéis Recebidos") -> 0 | D29: =SUMIFS(Lancamentos!$D:$D,Lancamentos!$A:$A,">="&DATE($I$6,6,1),Lancamentos!$A:$A,"<"&EDATE(DATE($I$6,6,1),1),Lancamentos!$C:$C,"Instrução / Educação")+SUMIFS(Lancamentos!$D:$D,Lancamentos!$A:$A,">="&DATE($I$6,6,1),Lancamentos!$A:$A,"<"&EDATE(DATE($I$6,6,1),1),Lancamentos!$C:$C,"Despesas Médicas e Odontológicas")+SUMIFS(Lancamentos!$D:$D,Lancamentos!$A:$A,">="&DATE($I$6,6,1),Lancamentos!$A:$A,"<"&EDATE(DATE($I$6,6,1),1),Lancamentos!$C:$C,"Previdência Privada (PGBL)")+SUMIFS(Lancamentos!$D:$D,Lancamentos!$A:$A,">="&DATE($I$6,6,1),Lancamentos!$A:$A,"<"&EDATE(DATE($I$6,6,1),1),Lancamentos!$C:$C,"Pensão Alimentícia Judicial") -> 0 | E29: =C29-D29 -> 0
B30: Jul | C30: =SUMIFS(Lancamentos!$D:$D,Lancamentos!$A:$A,">="&DATE($I$6,7,1),Lancamentos!$A:$A,"<"&EDATE(DATE($I$6,7,1),1),Lancamentos!$C:$C,"Rendimento de Trabalho Assalariado")+SUMIFS(Lancamentos!$D:$D,Lancamentos!$A:$A,">="&DATE($I$6,7,1),Lancamentos!$A:$A,"<"&EDATE(DATE($I$6,7,1),1),Lancamentos!$C:$C,"Aposentadorias e Pensões")+SUMIFS(Lancamentos!$D:$D,Lancamentos!$A:$A,">="&DATE($I$6,7,1),Lancamentos!$A:$A,"<"&EDATE(DATE($I$6,7,1),1),Lancamentos!$C:$C,"Aluguéis Recebidos") -> 0 | D30: =SUMIFS(Lancamentos!$D:$D,Lancamentos!$A:$A,">="&DATE($I$6,7,1),Lancamentos!$A:$A,"<"&EDATE(DATE($I$6,7,1),1),Lancamentos!$C:$C,"Instrução / Educação")+SUMIFS(Lancamentos!$D:$D,Lancamentos!$A:$A,">="&DATE($I$6,7,1),Lancamentos!$A:$A,"<"&EDATE(DATE($I$6,7,1),1),Lancamentos!$C:$C,"Despesas Médicas e Odontológicas")+SUMIFS(Lancamentos!$D:$D,Lancamentos!$A:$A,">="&DATE($I$6,7,1),Lancamentos!$A:$A,"<"&EDATE(DATE($I$6,7,1),1),Lancamentos!$C:$C,"Previdência Privada (PGBL)")+SUMIFS(Lancamentos!$D:$D,Lancamentos!$A:$A,">="&DATE($I$6,7,1),Lancamentos!$A:$A,"<"&EDATE(DATE($I$6,7,1),1),Lancamentos!$C:$C,"Pensão Alimentícia Judicial") -> 0 | E30: =C30-D30 -> 0
B31: Ago | C31: =SUMIFS(Lancamentos!$D:$D,Lancamentos!$A:$A,">="&DATE($I$6,8,1),Lancamentos!$A:$A,"<"&EDATE(DATE($I$6,8,1),1),Lancamentos!$C:$C,"Rendimento de Trabalho Assalariado")+SUMIFS(Lancamentos!$D:$D,Lancamentos!$A:$A,">="&DATE($I$6,8,1),Lancamentos!$A:$A,"<"&EDATE(DATE($I$6,8,1),1),Lancamentos!$C:$C,"Aposentadorias e Pensões")+SUMIFS(Lancamentos!$D:$D,Lancamentos!$A:$A,">="&DATE($I$6,8,1),Lancamentos!$A:$A,"<"&EDATE(DATE($I$6,8,1),1),Lancamentos!$C:$C,"Aluguéis Recebidos") -> 0 | D31: =SUMIFS(Lancamentos!$D:$D,Lancamentos!$A:$A,">="&DATE($I$6,8,1),Lancamentos!$A:$A,"<"&EDATE(DATE($I$6,8,1),1),Lancamentos!$C:$C,"Instrução / Educação")+SUMIFS(Lancamentos!$D:$D,Lancamentos!$A:$A,">="&DATE($I$6,8,1),Lancamentos!$A:$A,"<"&EDATE(DATE($I$6,8,1),1),Lancamentos!$C:$C,"Despesas Médicas e Odontológicas")+SUMIFS(Lancamentos!$D:$D,Lancamentos!$A:$A,">="&DATE($I$6,8,1),Lancamentos!$A:$A,"<"&EDATE(DATE($I$6,8,1),1),Lancamentos!$C:$C,"Previdência Privada (PGBL)")+SUMIFS(Lancamentos!$D:$D,Lancamentos!$A:$A,">="&DATE($I$6,8,1),Lancamentos!$A:$A,"<"&EDATE(DATE($I$6,8,1),1),Lancamentos!$C:$C,"Pensão Alimentícia Judicial") -> 0 | E31: =C31-D31 -> 0
B32: Set | C32: =SUMIFS(Lancamentos!$D:$D,Lancamentos!$A:$A,">="&DATE($I$6,9,1),Lancamentos!$A:$A,"<"&EDATE(DATE($I$6,9,1),1),Lancamentos!$C:$C,"Rendimento de Trabalho Assalariado")+SUMIFS(Lancamentos!$D:$D,Lancamentos!$A:$A,">="&DATE($I$6,9,1),Lancamentos!$A:$A,"<"&EDATE(DATE($I$6,9,1),1),Lancamentos!$C:$C,"Aposentadorias e Pensões")+SUMIFS(Lancamentos!$D:$D,Lancamentos!$A:$A,">="&DATE($I$6,9,1),Lancamentos!$A:$A,"<"&EDATE(DATE($I$6,9,1),1),Lancamentos!$C:$C,"Aluguéis Recebidos") -> 0 | D32: =SUMIFS(Lancamentos!$D:$D,Lancamentos!$A:$A,">="&DATE($I$6,9,1),Lancamentos!$A:$A,"<"&EDATE(DATE($I$6,9,1),1),Lancamentos!$C:$C,"Instrução / Educação")+SUMIFS(Lancamentos!$D:$D,Lancamentos!$A:$A,">="&DATE($I$6,9,1),Lancamentos!$A:$A,"<"&EDATE(DATE($I$6,9,1),1),Lancamentos!$C:$C,"Despesas Médicas e Odontológicas")+SUMIFS(Lancamentos!$D:$D,Lancamentos!$A:$A,">="&DATE($I$6,9,1),Lancamentos!$A:$A,"<"&EDATE(DATE($I$6,9,1),1),Lancamentos!$C:$C,"Previdência Privada (PGBL)")+SUMIFS(Lancamentos!$D:$D,Lancamentos!$A:$A,">="&DATE($I$6,9,1),Lancamentos!$A:$A,"<"&EDATE(DATE($I$6,9,1),1),Lancamentos!$C:$C,"Pensão Alimentícia Judicial") -> 0 | E32: =C32-D32 -> 0
B33: Out | C33: =SUMIFS(Lancamentos!$D:$D,Lancamentos!$A:$A,">="&DATE($I$6,10,1),Lancamentos!$A:$A,"<"&EDATE(DATE($I$6,10,1),1),Lancamentos!$C:$C,"Rendimento de Trabalho Assalariado")+SUMIFS(Lancamentos!$D:$D,Lancamentos!$A:$A,">="&DATE($I$6,10,1),Lancamentos!$A:$A,"<"&EDATE(DATE($I$6,10,1),1),Lancamentos!$C:$C,"Aposentadorias e Pensões")+SUMIFS(Lancamentos!$D:$D,Lancamentos!$A:$A,">="&DATE($I$6,10,1),Lancamentos!$A:$A,"<"&EDATE(DATE($I$6,10,1),1),Lancamentos!$C:$C,"Aluguéis Recebidos") -> 0 | D33: =SUMIFS(Lancamentos!$D:$D,Lancamentos!$A:$A,">="&DATE($I$6,10,1),Lancamentos!$A:$A,"<"&EDATE(DATE($I$6,10,1),1),Lancamentos!$C:$C,"Instrução / Educação")+SUMIFS(Lancamentos!$D:$D,Lancamentos!$A:$A,">="&DATE($I$6,10,1),Lancamentos!$A:$A,"<"&EDATE(DATE($I$6,10,1),1),Lancamentos!$C:$C,"Despesas Médicas e Odontológicas")+SUMIFS(Lancamentos!$D:$D,Lancamentos!$A:$A,">="&DATE($I$6,10,1),Lancamentos!$A:$A,"<"&EDATE(DATE($I$6,10,1),1),Lancamentos!$C:$C,"Previdência Privada (PGBL)")+SUMIFS(Lancamentos!$D:$D,Lancamentos!$A:$A,">="&DATE($I$6,10,1),Lancamentos!$A:$A,"<"&EDATE(DATE($I$6,10,1),1),Lancamentos!$C:$C,"Pensão Alimentícia Judicial") -> 0 | E33: =C33-D33 -> 0
B34: Nov | C34: =SUMIFS(Lancamentos!$D:$D,Lancamentos!$A:$A,">="&DATE($I$6,11,1),Lancamentos!$A:$A,"<"&EDATE(DATE($I$6,11,1),1),Lancamentos!$C:$C,"Rendimento de Trabalho Assalariado")+SUMIFS(Lancamentos!$D:$D,Lancamentos!$A:$A,">="&DATE($I$6,11,1),Lancamentos!$A:$A,"<"&EDATE(DATE($I$6,11,1),1),Lancamentos!$C:$C,"Aposentadorias e Pensões")+SUMIFS(Lancamentos!$D:$D,Lancamentos!$A:$A,">="&DATE($I$6,11,1),Lancamentos!$A:$A,"<"&EDATE(DATE($I$6,11,1),1),Lancamentos!$C:$C,"Aluguéis Recebidos") -> 0 | D34: =SUMIFS(Lancamentos!$D:$D,Lancamentos!$A:$A,">="&DATE($I$6,11,1),Lancamentos!$A:$A,"<"&EDATE(DATE($I$6,11,1),1),Lancamentos!$C:$C,"Instrução / Educação")+SUMIFS(Lancamentos!$D:$D,Lancamentos!$A:$A,">="&DATE($I$6,11,1),Lancamentos!$A:$A,"<"&EDATE(DATE($I$6,11,1),1),Lancamentos!$C:$C,"Despesas Médicas e Odontológicas")+SUMIFS(Lancamentos!$D:$D,Lancamentos!$A:$A,">="&DATE($I$6,11,1),Lancamentos!$A:$A,"<"&EDATE(DATE($I$6,11,1),1),Lancamentos!$C:$C,"Previdência Privada (PGBL)")+SUMIFS(Lancamentos!$D:$D,Lancamentos!$A:$A,">="&DATE($I$6,11,1),Lancamentos!$A:$A,"<"&EDATE(DATE($I$6,11,1),1),Lancamentos!$C:$C,"Pensão Alimentícia Judicial") -> 0 | E34: =C34-D34 -> 0
B35: Dez | C35: =SUMIFS(Lancamentos!$D:$D,Lancamentos!$A:$A,">="&DATE($I$6,12,1),Lancamentos!$A:$A,"<"&EDATE(DATE($I$6,12,1),1),Lancamentos!$C:$C,"Rendimento de Trabalho Assalariado")+SUMIFS(Lancamentos!$D:$D,Lancamentos!$A:$A,">="&DATE($I$6,12,1),Lancamentos!$A:$A,"<"&EDATE(DATE($I$6,12,1),1),Lancamentos!$C:$C,"Aposentadorias e Pensões")+SUMIFS(Lancamentos!$D:$D,Lancamentos!$A:$A,">="&DATE($I$6,12,1),Lancamentos!$A:$A,"<"&EDATE(DATE($I$6,12,1),1),Lancamentos!$C:$C,"Aluguéis Recebidos") -> 0 | D35: =SUMIFS(Lancamentos!$D:$D,Lancamentos!$A:$A,">="&DATE($I$6,12,1),Lancamentos!$A:$A,"<"&EDATE(DATE($I$6,12,1),1),Lancamentos!$C:$C,"Instrução / Educação")+SUMIFS(Lancamentos!$D:$D,Lancamentos!$A:$A,">="&DATE($I$6,12,1),Lancamentos!$A:$A,"<"&EDATE(DATE($I$6,12,1),1),Lancamentos!$C:$C,"Despesas Médicas e Odontológicas")+SUMIFS(Lancamentos!$D:$D,Lancamentos!$A:$A,">="&DATE($I$6,12,1),Lancamentos!$A:$A,"<"&EDATE(DATE($I$6,12,1),1),Lancamentos!$C:$C,"Previdência Privada (PGBL)")+SUMIFS(Lancamentos!$D:$D,Lancamentos!$A:$A,">="&DATE($I$6,12,1),Lancamentos!$A:$A,"<"&EDATE(DATE($I$6,12,1),1),Lancamentos!$C:$C,"Pensão Alimentícia Judicial") -> 0 | E35: =C35-D35 -> 0
B37: Fonte: lançamentos registrados na aba Lancamentos. Os valores são uma estimativa gerencial e devem ser conferidos com a legislação e documentos oficiais.
G39: COMPOSIÇÃO POR TIPO
G40: Tipo | H40: Valor
G41: Tributável | H41: =B9 -> 6500
G42: Isento | H42: =E9 -> 1200
G43: Dedução | H43: =H9 -> 800
